.coveragerc
.editorconfig
.gitignore
.travis.yml
LICENSE
README.md
pyproject.toml
requirements.txt
requirements_dev.txt
setup.cfg
setup.py
.github/workflows/python-publish.yml
democritus_csv/__init__.py
democritus_csv/csv_data.py
democritus_csv/csv_data_temp_utils.py
democritus_csv.egg-info/PKG-INFO
democritus_csv.egg-info/SOURCES.txt
democritus_csv.egg-info/dependency_links.txt
democritus_csv.egg-info/requires.txt
democritus_csv.egg-info/top_level.txt
democritus_csv.egg-info/zip-safe
tests/__init__.py
tests/test_csv_data.py